topsis/__init__.py
topsis/__main__.py
Topsis_Raghav_102218075-1.0.0.dist-info/METADATA
Topsis_Raghav_102218075-1.0.0.dist-info/WHEEL
Topsis_Raghav_102218075-1.0.0.dist-info/top_level.txt
Topsis_Raghav_102218075-1.0.0.dist-info/RECORD
