Metadata-Version: 2.1
Name: Topsis-Raghav-102218075
Version: 1.0.0
Summary: This package implements the Technique for Order of Preference by Similarity to Ideal Solution (TOPSIS) method.
Home-page: https://github.com/raghavsharma2865/Topsis-Raghav-102218075
Author: Raghav Sharma
Author-email: raghavsharma2865@gmail.com
License: MIT
Classifier: License :: OSI Approved :: MIT License
Classifier: Programming Language :: Python :: 3.6
Classifier: Programming Language :: Python :: 3.7
Classifier: Programming Language :: Python :: 3.8
Classifier: Programming Language :: Python :: 3.9
Classifier: Programming Language :: Python :: 3.10
Classifier: Programming Language :: Python :: 3.11
Classifier: Operating System :: OS Independent
Classifier: Intended Audience :: Developers
Classifier: Topic :: Software Development :: Libraries :: Python Modules
Requires-Dist: pandas >=1.0
Requires-Dist: numpy >=1.18
